LICENSE.txt
MANIFEST.in
README.rst
setup.py
dialog_py/__init__.py
dialog_py/dialog.py
dialog_py/exceptions.py
dialog_py/helpers.py
dialog_py/native.py
dialog_py/types.py
dialog_py.egg-info/PKG-INFO
dialog_py.egg-info/SOURCES.txt
dialog_py.egg-info/dependency_links.txt
dialog_py.egg-info/top_level.txt